shrinkcircle/__init__.py
shrinkcircle/shrinkcircle.py
shrinkcircle-0.2.dist-info/LICENSE
shrinkcircle-0.2.dist-info/METADATA
shrinkcircle-0.2.dist-info/WHEEL
shrinkcircle-0.2.dist-info/top_level.txt
shrinkcircle-0.2.dist-info/RECORD
