Metadata-Version: 2.1
Name: shrinkcircle
Version: 0.2
Summary: A package implementing an algorithm where there is a unit circle, and the circle contracts towards a point within the circle.
Home-page: https://github.com/rauta0127/shrinkcircle
Author: rauta0127
License: MIT
License-File: LICENSE
